git_diff/__init__.py
git_diff/__main__.py
git_diff/deal_diff.py
vestpackage/__init__.py
vestpackage/__main__.py
vestpackage/replace_package.py
gitdiff-1.0.1.dist-info/LICENSE
gitdiff-1.0.1.dist-info/METADATA
gitdiff-1.0.1.dist-info/WHEEL
gitdiff-1.0.1.dist-info/entry_points.txt
gitdiff-1.0.1.dist-info/top_level.txt
gitdiff-1.0.1.dist-info/RECORD
